vedro_shared_resource/__init__.py
vedro_shared_resource/py.typed
vedro_shared_resource-0.2.1.dist-info/LICENSE
vedro_shared_resource-0.2.1.dist-info/METADATA
vedro_shared_resource-0.2.1.dist-info/WHEEL
vedro_shared_resource-0.2.1.dist-info/top_level.txt
vedro_shared_resource-0.2.1.dist-info/RECORD
