Metadata-Version: 2.2
Name: vedro-shared-resource
Version: 0.2.1
Summary: A decorator for sharing costly resources between tests efficiently
Home-page: https://github.com/vedro-universe/vedro-shared-resource
Author: Nikita Tsvetkov
Author-email: tsv1@fastmail.com
License: Apache-2.0
Project-URL: Docs, https://github.com/vedro-universe/vedro-shared-resource
Project-URL: GitHub, https://github.com/vedro-universe/vedro-shared-resource
Classifier: License :: OSI Approved :: Apache Software License
Classifier: Programming Language :: Python :: 3.9
Classifier: Programming Language :: Python :: 3.10
Classifier: Programming Language :: Python :: 3.11
Classifier: Programming Language :: Python :: 3.12
Classifier: Programming Language :: Python :: 3.13
Classifier: Typing :: Typed
Requires-Python: >=3.8
License-File: LICENSE
Requires-Dist: vedro<2.0,>=1.13
Requires-Dist: async-lru<3.0,>=2.0
Dynamic: author
Dynamic: author-email
Dynamic: classifier
Dynamic: description
Dynamic: description-content-type
Dynamic: home-page
Dynamic: license
Dynamic: project-url
Dynamic: requires-dist
Dynamic: requires-python
Dynamic: summary
